eufySecurityApi/__init__.py
eufySecurityApi/api.py
eufySecurityApi/cli.py
eufySecurityApi/const.py
eufySecurityApi/model.py
eufySecurityApi/utils.py
eufy_security_api_rihan-0.1.4.dist-info/LICENSE
eufy_security_api_rihan-0.1.4.dist-info/METADATA
eufy_security_api_rihan-0.1.4.dist-info/WHEEL
eufy_security_api_rihan-0.1.4.dist-info/top_level.txt
eufy_security_api_rihan-0.1.4.dist-info/RECORD
