Metadata-Version: 2.1
Name: eufy-security-api-rihan
Version: 0.1.4
Summary: Cover the http API for eufy security devices
Home-page: https://github.com/Rihan9/eufySecurityApi
Author: Rihan
Author-email: aleatza@gmail.com
License: MIT License
Platform: UNKNOWN
Classifier: Programming Language :: Python :: 3
Classifier: License :: OSI Approved :: MIT License
Classifier: Operating System :: OS Independent
Requires-Python: >=3.6
Requires-Dist: requests
Requires-Dist: click
Requires-Dist: pytz
Requires-Dist: setuptools
Requires-Dist: asyncio
